{"timestamp": "2026-01-18T07:47:43.568344", "data": [{"time": "2026-01-18 00:00:00", "wave_height": 1.84, "wave_period": 11.8, "wave_direction": 205, "wind_wave_height": 0.0, "swell_wave_height": 1.82, "swell_wave_period": 9.75, "latitude": -17.85, "longitude": -71.15}, {"time": "2026-01-18 01:00:00", "wave_height": 1.84, "wave_period": 11.75, "wave_direction": 205, "wind_wave_height": 0.0, "swell_wave_height": 1.82, "swell_wave_period": 9.65, "latitude": -17.85, "longitude": -71.15}, {"time": "2026-01-18 02:00:00", "wave_height": 1.84, "wave_period": 11.7, "wave_direction": 205, "wind_wave_height": 0.0, "swell_wave_height": 1.82, "swell_wave_period": 9.65, "latitude": -17.85, "longitude": -71.15}, {"time": "2026-01-18 03:00:00", "wave_height": 1.84, "wave_period": 11.7, "wave_direction": 205, "wind_wave_height": 0.0, "swell_wave_height": 1.82, "swell_wave_period": 9.65, "latitude": -17.85, "longitude": -71.15}, {"time": "2026-01-18 04:00:00", "wave_height": 1.84, "wave_period": 11.7, "wave_direction": 205, "wind_wave_height": 0.0, "swell_wave_height": 1.82, "swell_wave_period": 9.65, "latitude": -17.85, "longitude": -71.15}, {"time": "2026-01-18 05:00:00", "wave_height": 1.84, "wave_period": 11.65, "wave_direction": 205, "wind_wave_height": 0.0, "swell_wave_height": 1.8, "swell_wave_period": 9.6, "latitude": -17.85, "longitude": -71.15}, {"time": "2026-01-18 06:00:00", "wave_height": 1.84, "wave_period": 11.65, "wave_direction": 205, "wind_wave_height": 0.0, "swell_wave_height": 1.8, "swell_wave_period": 9.6, "latitude": -17.85, "longitude": -71.15}, {"time": "2026-01-18 07:00:00", "wave_height": 1.84, "wave_period": 11.65, "wave_direction": 205, "wind_wave_height": 0.0, "swell_wave_height": 1.8, "swell_wave_period": 9.6, "latitude": -17.85, "longitude": -71.15}, {"time": "2026-01-18 08:00:00", "wave_height": 1.84, "wave_period": 11.65, "wave_direction": 205, "wind_wave_height": 0.02, "swell_wave_height": 1.8, "swell_wave_period": 9.65, "latitude": -17.85, "longitude": -71.15}, {"time": "2026-01-18 09:00:00", "wave_height": 1.84, "wave_period": 11.65, "wave_direction": 205, "wind_wave_height": 0.02, "swell_wave_height": 1.8, "swell_wave_period": 9.65, "latitude": -17.85, "longitude": -71.15}, {"time": "2026-01-18 10:00:00", "wave_height": 1.84, "wave_period": 11.65, "wave_direction": 205, "wind_wave_height": 0.04, "swell_wave_height": 1.8, "swell_wave_period": 9.65, "latitude": -17.85, "longitude": -71.15}, {"time": "2026-01-18 11:00:00", "wave_height": 1.82, "wave_period": 11.6, "wave_direction": 205, "wind_wave_height": 0.06, "swell_wave_height": 1.78, "swell_wave_period": 9.6, "latitude": -17.85, "longitude": -71.15}, {"time": "2026-01-18 12:00:00", "wave_height": 1.82, "wave_period": 11.55, "wave_direction": 205, "wind_wave_height": 0.08, "swell_wave_height": 1.78, "swell_wave_period": 9.55, "latitude": -17.85, "longitude": -71.15}, {"time": "2026-01-18 13:00:00", "wave_height": 1.8, "wave_period": 11.5, "wave_direction": 205, "wind_wave_height": 0.08, "swell_wave_height": 1.76, "swell_wave_period": 9.5, "latitude": -17.85, "longitude": -71.15}, {"time": "2026-01-18 14:00:00", "wave_height": 1.76, "wave_period": 11.4, "wave_direction": 206, "wind_wave_height": 0.1, "swell_wave_height": 1.72, "swell_wave_period": 9.4, "latitude": -17.85, "longitude": -71.15}, {"time": "2026-01-18 15:00:00", "wave_height": 1.74, "wave_period": 11.35, "wave_direction": 206, "wind_wave_height": 0.1, "swell_wave_height": 1.7, "swell_wave_period": 9.3, "latitude": -17.85, "longitude": -71.15}, {"time": "2026-01-18 16:00:00", "wave_height": 1.72, "wave_period": 11.3, "wave_direction": 206, "wind_wave_height": 0.08, "swell_wave_height": 1.68, "swell_wave_period": 9.2, "latitude": -17.85, "longitude": -71.15}, {"time": "2026-01-18 17:00:00", "wave_height": 1.68, "wave_period": 11.2, "wave_direction": 206, "wind_wave_height": 0.04, "swell_wave_height": 1.64, "swell_wave_period": 9.15, "latitude": -17.85, "longitude": -71.15}, {"time": "2026-01-18 18:00:00", "wave_height": 1.66, "wave_period": 11.15, "wave_direction": 206, "wind_wave_height": 0.02, "swell_wave_height": 1.62, "swell_wave_period": 9.05, "latitude": -17.85, "longitude": -71.15}, {"time": "2026-01-18 19:00:00", "wave_height": 1.64, "wave_period": 11.1, "wave_direction": 206, "wind_wave_height": 0.02, "swell_wave_height": 1.6, "swell_wave_period": 9.0, "latitude": -17.85, "longitude": -71.15}, {"time": "2026-01-18 20:00:00", "wave_height": 1.6, "wave_period": 11.0, "wave_direction": 206, "wind_wave_height": 0.02, "swell_wave_height": 1.58, "swell_wave_period": 8.95, "latitude": -17.85, "longitude": -71.15}, {"time": "2026-01-18 21:00:00", "wave_height": 1.58, "wave_period": 10.95, "wave_direction": 206, "wind_wave_height": 0.02, "swell_wave_height": 1.56, "swell_wave_period": 8.9, "latitude": -17.85, "longitude": -71.15}, {"time": "2026-01-18 22:00:00", "wave_height": 1.58, "wave_period": 10.9, "wave_direction": 206, "wind_wave_height": 0.02, "swell_wave_height": 1.56, "swell_wave_period": 8.85, "latitude": -17.85, "longitude": -71.15}, {"time": "2026-01-18 23:00:00", "wave_height": 1.58, "wave_period": 10.85, "wave_direction": 206, "wind_wave_height": 0.02, "swell_wave_height": 1.56, "swell_wave_period": 8.8, "latitude": -17.85, "longitude": -71.15}]}